japandata/__init__.py
japandata/utils.py
japandata/download/__init__.py
japandata/download/download.py
japandata/indices/__init__.py
japandata/indices/indices.py
japandata/maps/__init__.py
japandata/maps/maps.py
japandata/population/__init__.py
japandata/population/population.py
japandata/readings/__init__.py
japandata/readings/readings.py
japandata-0.5.2.dist-info/LICENSE.md
japandata-0.5.2.dist-info/METADATA
japandata-0.5.2.dist-info/WHEEL
japandata-0.5.2.dist-info/top_level.txt
japandata-0.5.2.dist-info/RECORD
