Metadata-Version: 2.1
Name: japandata
Version: 0.5.2
Summary: Geographic data about Japan
Author: Sam Passaglia
Project-URL: Homepage, https://github.com/passaglia/japandata
Project-URL: Bug Tracker, https://github.com/passaglia/japandata/issues
Classifier: Programming Language :: Python :: 3
Classifier: Operating System :: OS Independent
Classifier: License :: OSI Approved :: MIT License
Requires-Python: >=3.8
License-File: LICENSE.md
Requires-Dist: numpy
Requires-Dist: romkan
Requires-Dist: jaconv
Requires-Dist: geopandas
Requires-Dist: pandas
Requires-Dist: topojson
Requires-Dist: shapely
Requires-Dist: tqdm
Requires-Dist: openpyxl
Requires-Dist: xlrd
Requires-Dist: pyarrow
Requires-Dist: rich
